coregio/__init__.py
coregio/registry_api.py
coregio/registry_auth.py
coregio/utils.py
coregio-0.7.1.dist-info/LICENSE.txt
coregio-0.7.1.dist-info/METADATA
coregio-0.7.1.dist-info/WHEEL
coregio-0.7.1.dist-info/top_level.txt
coregio-0.7.1.dist-info/RECORD
