Metadata-Version: 2.1
Name: coregio
Version: 0.7.1
Summary: Python container registry API library.
Author-email: Ales Raszka <araszka@redhat.com>
License: Copyright (c) 2023 Ales Raszka
Project-URL: Homepage, https://github.com/Allda/coregio
Project-URL: Bug Tracker, https://github.com/Allda/coregio/issues
Classifier: Development Status :: 4 - Beta
Classifier: Intended Audience :: Developers
Classifier: Natural Language :: English
Classifier: Programming Language :: Python :: 3
Classifier: Programming Language :: Python :: 3.8
Classifier: Programming Language :: Python :: 3.9
Classifier: Programming Language :: Python :: 3.10
Classifier: Programming Language :: Python :: 3.11
Classifier: Topic :: Internet :: Proxy Servers
Classifier: Topic :: Internet :: WWW/HTTP :: HTTP Servers
Classifier: Topic :: Software Development :: Libraries
Classifier: Topic :: Software Development :: Libraries :: Python Modules
Classifier: Topic :: Utilities
Requires-Python: >=3.8
License-File: LICENSE.txt
Requires-Dist: requests >=2.31.0
Provides-Extra: coregio-dev
Requires-Dist: yamllint >=1.32.0 ; extra == 'coregio-dev'
Requires-Dist: bandit >=1.7.5 ; extra == 'coregio-dev'
Requires-Dist: pylint >=2.17.4 ; extra == 'coregio-dev'
Requires-Dist: pytest-cov >=4.1.0 ; extra == 'coregio-dev'
Requires-Dist: black >=23.3.0 ; extra == 'coregio-dev'
Requires-Dist: mypy >=1.3.0 ; extra == 'coregio-dev'
Requires-Dist: pytest >=7.3.1 ; extra == 'coregio-dev'
Provides-Extra: tox
Requires-Dist: tox-pdm >=0.6.1 ; extra == 'tox'
Requires-Dist: tox >=4.5.2 ; extra == 'tox'
